mytheme/__init__.py
mytheme/_version.py
mytheme/labextension/build_log.json
mytheme/labextension/package.json
mytheme/labextension/static/lib_index_js.d27b31ae4fcb5ae5bc00.js
mytheme/labextension/static/lib_index_js.d27b31ae4fcb5ae5bc00.js.map
mytheme/labextension/static/remoteEntry.8c75ca8000e4f7a886dd.js
mytheme/labextension/static/remoteEntry.8c75ca8000e4f7a886dd.js.map
mytheme/labextension/static/style.js
mytheme/labextension/themes/mytheme/index.css
mytheme/labextension/themes/mytheme/index.js
mytheme-0.1.0.data/data/share/jupyter/labextensions/mytheme/build_log.json
mytheme-0.1.0.data/data/share/jupyter/labextensions/mytheme/install.json
mytheme-0.1.0.data/data/share/jupyter/labextensions/mytheme/package.json
mytheme-0.1.0.data/data/share/jupyter/labextensions/mytheme/static/lib_index_js.d27b31ae4fcb5ae5bc00.js
mytheme-0.1.0.data/data/share/jupyter/labextensions/mytheme/static/lib_index_js.d27b31ae4fcb5ae5bc00.js.map
mytheme-0.1.0.data/data/share/jupyter/labextensions/mytheme/static/remoteEntry.8c75ca8000e4f7a886dd.js
mytheme-0.1.0.data/data/share/jupyter/labextensions/mytheme/static/remoteEntry.8c75ca8000e4f7a886dd.js.map
mytheme-0.1.0.data/data/share/jupyter/labextensions/mytheme/static/style.js
mytheme-0.1.0.data/data/share/jupyter/labextensions/mytheme/themes/mytheme/index.css
mytheme-0.1.0.data/data/share/jupyter/labextensions/mytheme/themes/mytheme/index.js
mytheme-0.1.0.dist-info/LICENSE
mytheme-0.1.0.dist-info/METADATA
mytheme-0.1.0.dist-info/WHEEL
mytheme-0.1.0.dist-info/top_level.txt
mytheme-0.1.0.dist-info/RECORD
